textlink/__init__.py
textlink-0.0.1.dist-info/METADATA
textlink-0.0.1.dist-info/WHEEL
textlink-0.0.1.dist-info/licenses/LICENSE
textlink-0.0.1.dist-info/RECORD
