Metadata-Version: 2.1
Name: textlink
Version: 0.0.1
Summary: Python library that helps you send SMS using TextLink API
Author-email: TextLink <help@textlinksms.com>
License-Expression: MIT
License-File: LICENSE
Keywords: api,api-client,bulk-sms,simple-sms,sms,sms-api,sms-gateway,sms-verification,text-message,user-verification
Classifier: License :: OSI Approved :: MIT License
Classifier: Operating System :: OS Independent
Classifier: Programming Language :: Python :: 3.6
Classifier: Programming Language :: Python :: 3.7
Classifier: Programming Language :: Python :: 3.8
Classifier: Programming Language :: Python :: 3.9
Classifier: Programming Language :: Python :: 3.10
Classifier: Programming Language :: Python :: 3.11
Classifier: Programming Language :: Python :: 3.12
Requires-Python: >=3.6
Requires-Dist: requests
